sipc_xethhung12/__init__.py
sipc_xethhung12/__main__.py
sipc_xethhung12/devices.yaml
sipc_xethhung12/sipc.py
sipc_xethhung12/cmd/__init__.py
sipc_xethhung12/cmd/cast.py
sipc_xethhung12/cmd/subscribeCmd.py
sipc_xethhung12/utils/kafka/__init__.py
sipc_xethhung12/utils/kafka/kafkaUtils.py
sipc_xethhung12-0.0.8.dist-info/METADATA
sipc_xethhung12-0.0.8.dist-info/WHEEL
sipc_xethhung12-0.0.8.dist-info/RECORD
