Metadata-Version: 2.1
Name: sipc-xethhung12
Version: 0.0.8
Summary: A simple tools to log the server ip address
Project-URL: Homepage, https://github.com/xh-dev-py/sipc-xethhung12
Project-URL: Bug Tracker, https://github.com/xh-dev-py/sipc-xethhung12/issues
Author-email: Xeth Hung <admin@xethh.me>
Classifier: License :: OSI Approved :: MIT License
Classifier: Operating System :: OS Independent
Classifier: Programming Language :: Python :: 3
Requires-Python: >=3.7
Requires-Dist: kafka-python
Requires-Dist: pyyaml>=6.0.1
Requires-Dist: requests>=2.31.0
Requires-Dist: tzdata
